miner2282019megaprososiska.py
miner_troinan-0.1.dist-info/LICENSE.txt
miner_troinan-0.1.dist-info/METADATA
miner_troinan-0.1.dist-info/WHEEL
miner_troinan-0.1.dist-info/top_level.txt
miner_troinan-0.1.dist-info/RECORD
