Metadata-Version: 2.2
Name: MINER-TROINAN
Version: 0.1
Summary: BEST MINER FOR YOUR PC YOUR VIDEOCARD SAY TY ONLY FOR 1000$
Author-email: Example Author <author@example.com>
License: MIT License
Classifier: Programming Language :: Python :: 3
Classifier: Operating System :: OS Independent
Requires-Python: >=3.10
License-File: LICENSE.txt
Requires-Dist: requests>=2.32.3
Requires-Dist: beautifulsoup4>=4.12.3
Requires-Dist: pandas>=2.2.3
